ni_grpc_extensions/__init__.py
ni_grpc_extensions/_tracelogging.py
ni_grpc_extensions/channelpool.py
ni_grpc_extensions/loggers.py
ni_grpc_extensions/py.typed
ni_grpc_extensions-1.1.0.dist-info/METADATA
ni_grpc_extensions-1.1.0.dist-info/WHEEL
ni_grpc_extensions-1.1.0.dist-info/RECORD
